gama_cli/__init__.py
gama_cli/banner.py
gama_cli/cli.py
gama_cli/helpers.py
gama_cli/docker/gs/docker-compose.cache.yaml
gama_cli/docker/gs/docker-compose.dev.yaml
gama_cli/docker/gs/docker-compose.network-host.yaml
gama_cli/docker/gs/docker-compose.network-shared.yaml
gama_cli/docker/gs/docker-compose.prod.yaml
gama_cli/docker/gs/docker-compose.yaml
gama_cli/docker/vessel/docker-compose.cache.yaml
gama_cli/docker/vessel/docker-compose.dev.yaml
gama_cli/docker/vessel/docker-compose.network-host.yaml
gama_cli/docker/vessel/docker-compose.network-shared.yaml
gama_cli/docker/vessel/docker-compose.prod.yaml
gama_cli/docker/vessel/docker-compose.variant.armidale.yaml
gama_cli/docker/vessel/docker-compose.variant.austal_m_usv.yaml
gama_cli/docker/vessel/docker-compose.variant.blue_boat.yaml
gama_cli/docker/vessel/docker-compose.variant.dmak.yaml
gama_cli/docker/vessel/docker-compose.variant.educat.yaml
gama_cli/docker/vessel/docker-compose.variant.fremantle.yaml
gama_cli/docker/vessel/docker-compose.variant.mars.yaml
gama_cli/docker/vessel/docker-compose.variant.oracle_22.yaml
gama_cli/docker/vessel/docker-compose.variant.oracle_2_2.yaml
gama_cli/docker/vessel/docker-compose.variant.tack.yaml
gama_cli/docker/vessel/docker-compose.variant.tenggara.yaml
gama_cli/docker/vessel/docker-compose.variant.waveflyer.yaml
gama_cli/docker/vessel/docker-compose.variant.whiskey_bravo.yaml
gama_cli/docker/vessel/docker-compose.yaml
gama_cli/groups/__init__.py
gama_cli/groups/attach.py
gama_cli/groups/docker.py
gama_cli/groups/git.py
gama_cli/groups/gs.py
gama_cli/groups/misc.py
gama_cli/groups/setup.py
gama_cli/groups/vessel.py
gama_cli-4.5.1.dist-info/METADATA
gama_cli-4.5.1.dist-info/WHEEL
gama_cli-4.5.1.dist-info/entry_points.txt
gama_cli-4.5.1.dist-info/top_level.txt
gama_cli-4.5.1.dist-info/zip-safe
gama_cli-4.5.1.dist-info/RECORD
