Metadata-Version: 2.4
Name: gama_cli
Version: 4.5.1
Summary: A CLI for interacting with the GAMA platform
Home-page: https://github.com/Greenroom-Robotics/gama
Author: Greenroom Robotics
Author-email: team@greenroomrobotics.com
Maintainer: David Revay
Maintainer-email: david.revay@greenroomrobotics.com
License: Copyright (C) 2023, Greenroom Robotics
Keywords: colcon
Classifier: Development Status :: 3 - Alpha
Classifier: Environment :: Plugins
Classifier: Intended Audience :: Developers
Classifier: Programming Language :: Python
Classifier: Topic :: Software Development :: Build Tools
Requires-Dist: toml~=0.10
Requires-Dist: setuptools
Requires-Dist: colorama
Requires-Dist: click
Requires-Dist: python-on-whales
Requires-Dist: PyYAML
Requires-Dist: requests
Requires-Dist: gama_config
Requires-Dist: greenstream_config
